{"name":"CyrilQC","tagline":"Integration Test Framework","body":"Cyril Quality Centre\r\n--------------------\r\nIntegration test framework\r\n\r\nBuild\r\n-----\r\n    cd cyrilqc-core\r\n    ./gradle clean all\r\n\r\nRun\r\n---\r\n    unzip cyrilqc-*.zip\r\n    cyrilqc-*/bin/cyrilqc\r\n\r\nLicense\r\n-------\r\nThis software is distributed a dual license - GPL3 and proprietary license.\r\nSee http://www.gnu.org/licenses/gpl.html for open-source license details or contact\r\nus at cyril.sochor@gmail.com for proprietary license.\r\n\r\nSupport\r\n-------\r\nIn case you encounter issues running CyrilQC, please contact us at cyril.sochor@gmail.com\r\n\r\n","google":"","note":"Don't delete this file! It's used internally to help with page regeneration."}